jupyterlab_playback/__init__.py
jupyterlab_playback/_version.py
jupyterlab_playback/application.py
jupyterlab_playback/handlers.py
jupyterlab_playback/loader.py
jupyterlab_playback-0.1.8.data/data/etc/jupyter/jupyter_server_config.d/jupyterlab_playback.json
jupyterlab_playback-0.1.8.data/data/share/jupyter/labextensions/jupyterlab-playback/package.json
jupyterlab_playback-0.1.8.data/data/share/jupyter/labextensions/jupyterlab-playback/schemas/jupyterlab-playback/package.json.orig
jupyterlab_playback-0.1.8.data/data/share/jupyter/labextensions/jupyterlab-playback/schemas/jupyterlab-playback/plugin.json
jupyterlab_playback-0.1.8.data/data/share/jupyter/labextensions/jupyterlab-playback/static/645.90ba66bb2a6f960beffa.js
jupyterlab_playback-0.1.8.data/data/share/jupyter/labextensions/jupyterlab-playback/static/728.d866f2b1ee0f73eb5744.js
jupyterlab_playback-0.1.8.data/data/share/jupyter/labextensions/jupyterlab-playback/static/888.76f46d3eef9058c7d2fd.js
jupyterlab_playback-0.1.8.data/data/share/jupyter/labextensions/jupyterlab-playback/static/remoteEntry.4d392edd2188a142c5af.js
jupyterlab_playback-0.1.8.data/data/share/jupyter/labextensions/jupyterlab-playback/static/style.js
jupyterlab_playback-0.1.8.data/data/share/jupyter/labextensions/jupyterlab-playback/static/third-party-licenses.json
jupyterlab_playback-0.1.8.data/data/share/jupyter/labextensions/jupyterlab-playback/install.json
jupyterlab_playback-0.1.8.dist-info/METADATA
jupyterlab_playback-0.1.8.dist-info/WHEEL
jupyterlab_playback-0.1.8.dist-info/licenses/LICENSE
jupyterlab_playback-0.1.8.dist-info/RECORD
